{"version": 2.0, "questions": [{"question": "A solid cone having specific gravity 0.8 floats in water with apex down. Find the metacentre and stability of the cone. Diameter of the cone is 1 m and height of the cone is 2.9 m.", "answers": {"a": "-0.099", "b": "0.376", "c": "-0.278", "d": "0.327"}, "explanations": {"a": "", "b": "", "c": "", "d": ""}, "correctAnswer": "a", "difficulty": "beginner"}, {"question": "A solid cone having specific gravity 0.8 floats in water with apex down. Find the metacentre and stability of the cone. Diameter of the cone is 1 m and height of the cone is 1.2 m.", "answers": {"a": "0.477", "b": "0.327", "c": "0.08", "d": "0.187"}, "explanations": {"a": "", "b": "", "c": "", "d": ""}, "correctAnswer": "c", "difficulty": "beginner"}]}